thunderpack/__init__.py
thunderpack/common.py
thunderpack/compression.py
thunderpack/formats.py
thunderpack/supported.py
thunderpack/thunder.py
thunderpack/torch.py
thunderpack-0.0.2.dist-info/LICENSE
thunderpack-0.0.2.dist-info/METADATA
thunderpack-0.0.2.dist-info/WHEEL
thunderpack-0.0.2.dist-info/top_level.txt
thunderpack-0.0.2.dist-info/RECORD
