Metadata-Version: 2.1
Name: thunderpack
Version: 0.0.2
Summary: Dataset library for blazingly fast data loading and decoding
Author-email: Jose Javier Gonzalez Ortiz <josejg@mit.edu>
License: MIT License
Project-URL: Homepage, https://github.com/jjgo/thunderpack
Project-URL: Repository, https://github.com/jjgo/thunderpack
Keywords: thunderpack,formats,machine learning,encoding
Classifier: License :: OSI Approved :: MIT License
Classifier: Programming Language :: Python
Classifier: Programming Language :: Python :: 3
Requires-Python: >=3.9
License-File: LICENSE
Requires-Dist: lmdb
Requires-Dist: lmdbm
Requires-Dist: lz4
Requires-Dist: zstd
Requires-Dist: msgpack
Requires-Dist: pydantic
Requires-Dist: python-snappy
Requires-Dist: brotli
Requires-Dist: numpy
Requires-Dist: pyarrow
Requires-Dist: pandas
Requires-Dist: torch
Requires-Dist: Pillow
Requires-Dist: soundfile
Requires-Dist: pyyaml
Requires-Dist: msgpack-numpy
Provides-Extra: dev
Requires-Dist: black ; extra == 'dev'
Requires-Dist: bumpver ; extra == 'dev'
Requires-Dist: isort ; extra == 'dev'
Requires-Dist: pip-tools ; extra == 'dev'
Requires-Dist: pytest ; extra == 'dev'
Requires-Dist: pyright ; extra == 'dev'
